odoo10_addon_support_branding-10.0.1.0.0-py2.7-nspkg.pth
odoo/addons/support_branding/README.rst
odoo/addons/support_branding/__init__.py
odoo/addons/support_branding/__manifest__.py
odoo/addons/support_branding/data/ir_config_parameter.xml
odoo/addons/support_branding/i18n/nl.po
odoo/addons/support_branding/i18n/sl.po
odoo/addons/support_branding/i18n/support_branding.pot
odoo/addons/support_branding/static/description/icon.png
odoo/addons/support_branding/static/src/css/support_branding.css
odoo/addons/support_branding/static/src/js/support_branding.js
odoo/addons/support_branding/static/src/xml/base.xml
odoo/addons/support_branding/views/qweb.xml
odoo10_addon_support_branding-10.0.1.0.0.dist-info/DESCRIPTION.rst
odoo10_addon_support_branding-10.0.1.0.0.dist-info/METADATA
odoo10_addon_support_branding-10.0.1.0.0.dist-info/RECORD
odoo10_addon_support_branding-10.0.1.0.0.dist-info/WHEEL
odoo10_addon_support_branding-10.0.1.0.0.dist-info/metadata.json
odoo10_addon_support_branding-10.0.1.0.0.dist-info/namespace_packages.txt
odoo10_addon_support_branding-10.0.1.0.0.dist-info/top_level.txt
